dydxpy/__init__.py
dydxpy/proto/__init__.py
dydxpy/proto/amino/amino_pb2.py
dydxpy/proto/amino/amino_pb2.pyi
dydxpy/proto/amino/amino_pb2_grpc.py
dydxpy/proto/cosmos/app/runtime/v1alpha1/module_pb2.py
dydxpy/proto/cosmos/app/runtime/v1alpha1/module_pb2.pyi
dydxpy/proto/cosmos/app/runtime/v1alpha1/module_pb2_grpc.py
dydxpy/proto/cosmos/app/v1alpha1/config_pb2.py
dydxpy/proto/cosmos/app/v1alpha1/config_pb2.pyi
dydxpy/proto/cosmos/app/v1alpha1/config_pb2_grpc.py
dydxpy/proto/cosmos/app/v1alpha1/module_pb2.py
dydxpy/proto/cosmos/app/v1alpha1/module_pb2.pyi
dydxpy/proto/cosmos/app/v1alpha1/module_pb2_grpc.py
dydxpy/proto/cosmos/app/v1alpha1/query_pb2.py
dydxpy/proto/cosmos/app/v1alpha1/query_pb2.pyi
dydxpy/proto/cosmos/app/v1alpha1/query_pb2_grpc.py
dydxpy/proto/cosmos/auth/module/v1/module_pb2.py
dydxpy/proto/cosmos/auth/module/v1/module_pb2.pyi
dydxpy/proto/cosmos/auth/module/v1/module_pb2_grpc.py
dydxpy/proto/cosmos/auth/v1beta1/auth_pb2.py
dydxpy/proto/cosmos/auth/v1beta1/auth_pb2.pyi
dydxpy/proto/cosmos/auth/v1beta1/auth_pb2_grpc.py
dydxpy/proto/cosmos/auth/v1beta1/genesis_pb2.py
dydxpy/proto/cosmos/auth/v1beta1/genesis_pb2.pyi
dydxpy/proto/cosmos/auth/v1beta1/genesis_pb2_grpc.py
dydxpy/proto/cosmos/auth/v1beta1/query_pb2.py
dydxpy/proto/cosmos/auth/v1beta1/query_pb2.pyi
dydxpy/proto/cosmos/auth/v1beta1/query_pb2_grpc.py
dydxpy/proto/cosmos/auth/v1beta1/tx_pb2.py
dydxpy/proto/cosmos/auth/v1beta1/tx_pb2.pyi
dydxpy/proto/cosmos/auth/v1beta1/tx_pb2_grpc.py
dydxpy/proto/cosmos/authz/module/v1/module_pb2.py
dydxpy/proto/cosmos/authz/module/v1/module_pb2.pyi
dydxpy/proto/cosmos/authz/module/v1/module_pb2_grpc.py
dydxpy/proto/cosmos/authz/v1beta1/authz_pb2.py
dydxpy/proto/cosmos/authz/v1beta1/authz_pb2.pyi
dydxpy/proto/cosmos/authz/v1beta1/authz_pb2_grpc.py
dydxpy/proto/cosmos/authz/v1beta1/event_pb2.py
dydxpy/proto/cosmos/authz/v1beta1/event_pb2.pyi
dydxpy/proto/cosmos/authz/v1beta1/event_pb2_grpc.py
dydxpy/proto/cosmos/authz/v1beta1/genesis_pb2.py
dydxpy-0.4.0.post1.dist-info/LICENSE
dydxpy-0.4.0.post1.dist-info/METADATA
dydxpy-0.4.0.post1.dist-info/WHEEL
dydxpy-0.4.0.post1.dist-info/RECORD
