Metadata-Version: 2.1
Name: dydxpy
Version: 0.4.0.post1
Summary: Proto types and clients for dYdX v4 protocol
License: MIT
Author: John Huang
Author-email: contact@dydx.exchange
Requires-Python: >=3.8,<4.0
Classifier: License :: OSI Approved :: MIT License
Classifier: Programming Language :: Python :: 3
Classifier: Programming Language :: Python :: 3.8
Classifier: Programming Language :: Python :: 3.9
Classifier: Programming Language :: Python :: 3.10
Classifier: Programming Language :: Python :: 3.11
Requires-Dist: grpcio (>=1.54,<2.0)
Requires-Dist: grpcio-tools (>=1.54,<2.0)
Requires-Dist: protobuf (>=4.23,<5.0)
